Java8XinTexingTanjiu/README.md
Java8XinTexingTanjiu/__init__.py
Java8XinTexingTanjiu/__main__.py
Java8XinTexingTanjiu/file.epub
Java8XinTexingTanjiu/index.html
Java8XinTexingTanjiu/css/__init__.py
Java8XinTexingTanjiu/css/annotations.css
Java8XinTexingTanjiu/css/main.css
Java8XinTexingTanjiu/css/normalize.css
Java8XinTexingTanjiu/css/popup.css
Java8XinTexingTanjiu/font/__init__.py
Java8XinTexingTanjiu/font/fontello.eot
Java8XinTexingTanjiu/font/fontello.svg
Java8XinTexingTanjiu/font/fontello.ttf
Java8XinTexingTanjiu/font/fontello.woff
Java8XinTexingTanjiu/img/__init__.py
Java8XinTexingTanjiu/img/annotator-glyph-sprite.png
Java8XinTexingTanjiu/img/annotator-icon-sprite.png
Java8XinTexingTanjiu/img/apple-touch-icon.png
Java8XinTexingTanjiu/img/cancelfullscreen.png
Java8XinTexingTanjiu/img/close.png
Java8XinTexingTanjiu/img/fullscreen.png
Java8XinTexingTanjiu/img/loader.gif
Java8XinTexingTanjiu/img/menu-icon.png
Java8XinTexingTanjiu/img/save.png
Java8XinTexingTanjiu/img/saved.png
Java8XinTexingTanjiu/img/settings-s.png
Java8XinTexingTanjiu/img/settings.png
Java8XinTexingTanjiu/img/star.png
Java8XinTexingTanjiu/js/__init__.py
Java8XinTexingTanjiu/js/epub.js
Java8XinTexingTanjiu/js/epub.min.js
Java8XinTexingTanjiu/js/epub.min.map
Java8XinTexingTanjiu/js/hooks.min.js
Java8XinTexingTanjiu/js/hooks.min.map
Java8XinTexingTanjiu/js/reader.js
Java8XinTexingTanjiu/js/reader.js.map
Java8XinTexingTanjiu/js/reader.min.js
Java8XinTexingTanjiu/js/reader.min.map
Java8XinTexingTanjiu/js/hooks/__init__.py
Java8XinTexingTanjiu/js/hooks/extensions/__init__.py
Java8XinTexingTanjiu/js/hooks/extensions/highlight.js
Java8XinTexingTanjiu/js/libs/__init__.py
Java8XinTexingTanjiu/js/libs/jquery.min.js
Java8XinTexingTanjiu/js/libs/localforage.min.js
Java8XinTexingTanjiu/js/libs/screenfull.js
Java8XinTexingTanjiu/js/libs/screenfull.min.js
Java8XinTexingTanjiu/js/libs/zip.min.js
Java8XinTexingTanjiu/js/plugins/__init__.py
Java8XinTexingTanjiu/js/plugins/hypothesis.js
java8_xin_texing_tanjiu-2024.3.1.0.dist-info/METADATA
java8_xin_texing_tanjiu-2024.3.1.0.dist-info/WHEEL
java8_xin_texing_tanjiu-2024.3.1.0.dist-info/entry_points.txt
java8_xin_texing_tanjiu-2024.3.1.0.dist-info/top_level.txt
java8_xin_texing_tanjiu-2024.3.1.0.dist-info/RECORD
